maq
